PDatainstaller/__init__.py
PDatainstaller/installer.py
pdatainstaller-1.0.0.dist-info/licenses/LICENSE
pdatainstaller-1.0.0.dist-info/METADATA
pdatainstaller-1.0.0.dist-info/WHEEL
pdatainstaller-1.0.0.dist-info/top_level.txt
pdatainstaller-1.0.0.dist-info/RECORD
